hizashi_utils
