Metadata-Version: 1.1
Name: hizashi-utils
Version: 0.3.2
Summary: Utils for managing Django Hizashi environment
Home-page: https://github.com/dodobas/hizashi-utils
Author: Dražen Odobašić
Author-email: dodobasic@gmail.com
License: LICENSE.txt
Keywords: django hizashi utils helpers
Platform: UNKNOWN
Classifier: Development Status :: 3 - Alpha
Classifier: Environment :: Console
Classifier: Framework :: Django
Classifier: Intended Audience :: Developers
Classifier: License :: OSI Approved :: MIT License
Classifier: Programming Language :: Python :: 2.7
Classifier: Topic :: Utilities
